[
    {
        "Key": 1,
        "Value": [
            {
                "Code": "50014400",
                "Name": "پت لیمو یک لیتری 13500 فروش",
                "Count": "4 باکس",
                "Fee": "591,000",
                "Amount": "2,364,000",
                "RowDiscountValue": "108,744",
                "RowDiscountPercent": "4.6",
                "AfterDiscount": "2,255,256",
                "VAT": "202,973",
                "FinalAmount": "2,458,229"
            },
            {
                "Code": "50014500",
                "Name": "پت هلو یک لیتری 13500 فروش",
                "Count": "3 باکس",
                "Fee": "591,000",
                "Amount": "1,773,000",
                "RowDiscountValue": "81,558",
                "RowDiscountPercent": "4.6",
                "AfterDiscount": "1,691,442",
                "VAT": "152,230",
                "FinalAmount": "1,843,672"
            },
            {
                "Code": "50014700",
                "Name": "پت انار یک لیتری 13500 فروش",
                "Count": "1 باکس",
                "Fee": "591,000",
                "Amount": "591,000",
                "RowDiscountValue": "27,186",
                "RowDiscountPercent": "4.6",
                "AfterDiscount": "563,814",
                "VAT": "50,743",
                "FinalAmount": "614,557"
            }
        ]
    },
    {
        "Key": 2,
        "Value": [
            {
                "Code": "50014100",
                "Name": "شیشه هلو 12 عددی 8500فروش",
                "Count": "1 باکس",
                "Fee": "782,160",
                "Amount": "782,160",
                "RowDiscountValue": "0",
                "RowDiscountPercent": "0",
                "AfterDiscount": "782,160",
                "VAT": "70,394",
                "FinalAmount": "852,554"
            },
            {
                "Code": "50014400",
                "Name": "پت لیمو یک لیتری 13500 فروش",
                "Count": "1 باکس",
                "Fee": "591,000",
                "Amount": "591,000",
                "RowDiscountValue": "0",
                "RowDiscountPercent": "0",
                "AfterDiscount": "591,000",
                "VAT": "53,190",
                "FinalAmount": "644,190"
            },
            {
                "Code": "50014500",
                "Name": "پت هلو یک لیتری 13500 فروش",
                "Count": "1 باکس",
                "Fee": "591,000",
                "Amount": "591,000",
                "RowDiscountValue": "0",
                "RowDiscountPercent": "0",
                "AfterDiscount": "591,000",
                "VAT": "53,190",
                "FinalAmount": "644,190"
            }
        ]
    },
    {
        "Key": 3,
        "Value": [
            {
                "Code": "50014900",
                "Name": "پت سیب یک لیتری 13500 فروش",
                "Count": "1 باکس",
                "Fee": "591,000",
                "Amount": "591,000",
                "RowDiscountValue": "0",
                "RowDiscountPercent": "0",
                "AfterDiscount": "591,000",
                "VAT": "0",
                "FinalAmount": "591,000"
            },
            {
                "Code": "50016700",
                "Name": "پت هلو یک لیتری 13500 فروش",
                "Count": "1 باکس",
                "Fee": "613,758",
                "Amount": "613,758",
                "RowDiscountValue": "0",
                "RowDiscountPercent": "0",
                "AfterDiscount": "613,758",
                "VAT": "0",
                "FinalAmount": "613,758"
            }
        ]
    },
    {
        "Key": 4,
        "Value": [
            {
                "Code": "50028400",
                "Name": "پوشک کامل کامفلکس سایز3متوسط 14تایی(12بسته ای)",
                "Count": "1 کیسه",
                "Fee": "4,339,812",
                "Amount": "4,339,812",
                "RowDiscountValue": "86,796",
                "RowDiscountPercent": "2",
                "AfterDiscount": "4,253,016",
                "VAT": "0",
                "FinalAmount": "4,253,016"
            },
            {
                "Code": "50028600",
                "Name": "پوشک کامل کامفلکس سایز5خیلی بزرگ 10تایی(12بسته ای)",
                "Count": "1 کیسه",
                "Fee": "4,339,812",
                "Amount": "4,339,812",
                "RowDiscountValue": "86,796",
                "RowDiscountPercent": "2",
                "AfterDiscount": "4,253,016",
                "VAT": "0",
                "FinalAmount": "4,253,016"
            }
        ]
    },
    {
        "Key": 5,
        "Value": [
            {
                "Code": "50029800",
                "Name": "دریچه ترموستات پراید یرو4",
                "Count": "8 بسته",
                "Fee": "1,000,000",
                "Amount": "8,000,000",
                "RowDiscountValue": "0",
                "RowDiscountPercent": "0",
                "AfterDiscount": "8,000,000",
                "VAT": "0",
                "FinalAmount": "8,000,000"
            },
            {
                "Code": "50029800",
                "Name": "دریچه ترموستات پراید یرو4",
                "Count": "5 کارتن",
                "Fee": "1,000,0000",
                "Amount": "50,000,000",
                "RowDiscountValue": "0",
                "RowDiscountPercent": "0",
                "AfterDiscount": "50,000,000",
                "VAT": "0",
                "FinalAmount": "50,000,000"
            }
        ]
    }

]